LICENSE
README.md
setup.cfg
setup.py
hathorsdk/__init__.py
hathorsdk/burn_wallet_address.py
hathorsdk/get_configuration_string.py
hathorsdk/get_nft_owner.py
hathorsdk/get_received_htr_amount.py
hathorsdk/hathor_mint.py
hathorsdk/headless_wallet.py
hathorsdk/pinata.py
hathorsdk/schema_hathor_mint.py
hathorsdk/schema_nft_metadata.py
hathorsdk.egg-info/PKG-INFO
hathorsdk.egg-info/SOURCES.txt
hathorsdk.egg-info/dependency_links.txt
hathorsdk.egg-info/requires.txt
hathorsdk.egg-info/top_level.txt