Metadata-Version: 2.1
Name: hathorsdk
Version: 2021.12.29
Summary: A python package to interact with the Hathor blockchain. Specialised for NFT projects.
Home-page: https://github.com/Tall1n/hathor-sdk
Author: Tallin
Author-email: T4ll1n0@gmail.com
License: UNKNOWN
Project-URL: Bug Reports, https://github.com/Tall1n/hathor-sdk/issues
Project-URL: Funding, https://explorer.hathor.network/address/HFEkN7Wu6X6AoeF4CvwfLGCgviUqifvnoG
Platform: UNKNOWN
Classifier: Development Status :: 3 - Alpha
Classifier: Intended Audience :: Developers
Classifier: License :: OSI Approved :: MIT License
Classifier: Operating System :: OS Independent
Classifier: Programming Language :: Python :: 3
Classifier: Programming Language :: Python :: 3.7
Classifier: Programming Language :: Python :: 3.8
Classifier: Programming Language :: Python :: 3.9
Classifier: Programming Language :: Python :: 3.10
Classifier: Programming Language :: Python :: 3 :: Only
Requires-Python: >=3.7, <4
License-File: LICENSE
